cipherspy/__init__.py
cipherspy/exceptions.py
cipherspy/cipher/__init__.py
cipherspy/cipher/affine.py
cipherspy/cipher/base_cipher.py
cipherspy/cipher/caesar.py
cipherspy/cipher/hill.py
cipherspy/cipher/playfair.py
cipherspy/utilities/__init__.py
cipherspy-0.7.0.dist-info/LICENSE
cipherspy-0.7.0.dist-info/METADATA
cipherspy-0.7.0.dist-info/WHEEL
cipherspy-0.7.0.dist-info/top_level.txt
cipherspy-0.7.0.dist-info/RECORD
